nkhandic/__init__.py
nkhandic/nkhandic.py
nkhandic/dicdir/README.md
nkhandic/dicdir/char.bin
nkhandic/dicdir/dicrc
nkhandic/dicdir/matrix.bin
nkhandic/dicdir/mecabrc
nkhandic/dicdir/sys.dic
nkhandic/dicdir/unk.dic
nkhandic/dicdir/version
nkhandic-25.11.5.dist-info/licenses/LICENSE
nkhandic-25.11.5.dist-info/licenses/LICENSE.nkhandic
nkhandic-25.11.5.dist-info/METADATA
nkhandic-25.11.5.dist-info/WHEEL
nkhandic-25.11.5.dist-info/top_level.txt
nkhandic-25.11.5.dist-info/RECORD
