Metadata-Version: 2.4
Name: nkhandic
Version: 25.11.5
Summary: NK-HanDic package for installing via pip.
Author: Yoshinori Sugai
Author-email: okikirmui+github@gmail.com
License: MIT License
Project-URL: Repository, https://github.com/okikirmui/nkhandic-py
Keywords: nkhandic,MeCab,North Korean Language,morphological analysis,morphological analysis dictionary,korean text processing
Classifier: License :: OSI Approved :: MIT License
Classifier: Programming Language :: Python
Classifier: Natural Language :: Korean
Classifier: Operating System :: OS Independent
Classifier: Topic :: Text Processing
Requires-Python: >=3.8
License-File: LICENSE
License-File: LICENSE.nkhandic
Dynamic: license-file
